ycommon/__init__.py
ycommon/utils.py
ycommon/django_modules/__init__.py
ycommon/django_modules/newsletter/__init__.py
ycommon/django_modules/newsletter/admin.py
ycommon/django_modules/newsletter/apps.py
ycommon/django_modules/newsletter/forms.py
ycommon/django_modules/newsletter/models.py
ycommon/django_modules/newsletter/urls.py
ycommon/django_modules/newsletter/views.py
ycommon/django_modules/newsletter/migrations/0001_initial.py
ycommon/django_modules/newsletter/migrations/__init__.py
ycommon-0.0.8.dist-info/METADATA
ycommon-0.0.8.dist-info/WHEEL
ycommon-0.0.8.dist-info/top_level.txt
ycommon-0.0.8.dist-info/RECORD
