Metadata-Version: 2.1
Name: ycommon
Version: 0.0.8
Summary: Common utils
Author: Thomas De Bonnet
Author-email: thomasdebonnetpro@gmail.com
Classifier: Programming Language :: Python :: 3
Classifier: License :: OSI Approved :: MIT License
Classifier: Operating System :: OS Independent
Requires-Python: >=3
